twisted_raiser/__init__.py
twisted_raiser/raiser.py
twisted_raiser-2.0.0.dist-info/LICENSE
twisted_raiser-2.0.0.dist-info/WHEEL
twisted_raiser-2.0.0.dist-info/METADATA
twisted_raiser-2.0.0.dist-info/RECORD
